envfy/__init__.py
envfy/cli.py
envfy/core/__init__.py
envfy/core/cache.py
envfy/core/config.py
envfy/core/environment.py
envfy/core/manager.py
envfy/core/template.py
envfy/utils/__init__.py
envfy/utils/exceptions.py
envfy/utils/helpers.py
envfy/utils/output.py
envfy/utils/platform_support.py
envfy/utils/validators.py
envfy-1.3.0.dist-info/licenses/LICENSE
envfy-1.3.0.dist-info/METADATA
envfy-1.3.0.dist-info/WHEEL
envfy-1.3.0.dist-info/entry_points.txt
envfy-1.3.0.dist-info/top_level.txt
envfy-1.3.0.dist-info/RECORD
