Metadata-Version: 2.4
Name: envfy
Version: 1.3.0
Summary: Fast, precise, and user-friendly Python virtual environment management
Home-page: https://github.com/Pymmdrza/Package_envfy
Author: Mmdrza
Author-email: Pymmdrza@gmail.com
Project-URL: Bug Reports, https://github.com/envfy/envfy/issues
Project-URL: Source, https://github.com/envfy/envfy
Project-URL: Documentation, https://envfy.readthedocs.io/
Keywords: virtual environment virtualenv venv python package management cli
Classifier: Development Status :: 5 - Production/Stable
Classifier: Intended Audience :: Developers
Classifier: Topic :: Software Development :: Build Tools
Classifier: Topic :: System :: Installation/Setup
Classifier: License :: OSI Approved :: MIT License
Classifier: Programming Language :: Python :: 3
Classifier: Programming Language :: Python :: 3.7
Classifier: Programming Language :: Python :: 3.8
Classifier: Programming Language :: Python :: 3.9
Classifier: Programming Language :: Python :: 3.10
Classifier: Programming Language :: Python :: 3.11
Classifier: Programming Language :: Python :: 3.12
Classifier: Operating System :: OS Independent
Classifier: Environment :: Console
Requires-Python: >=3.7
License-File: LICENSE
Requires-Dist: click>=8.0.0
Requires-Dist: colorama>=0.4.4
Requires-Dist: rich>=12.0.0
Requires-Dist: virtualenv>=20.0.0
Requires-Dist: packaging>=21.0
Requires-Dist: psutil>=5.8.0
Requires-Dist: requests>=2.25.0
Requires-Dist: toml>=0.10.2
Requires-Dist: pyyaml>=6.0
Provides-Extra: dev
Requires-Dist: pytest>=6.2.0; extra == "dev"
Requires-Dist: pytest-cov>=2.12.0; extra == "dev"
Requires-Dist: black>=21.0.0; extra == "dev"
Requires-Dist: flake8>=3.9.0; extra == "dev"
Requires-Dist: mypy>=0.910; extra == "dev"
Requires-Dist: isort>=5.9.0; extra == "dev"
Requires-Dist: pre-commit>=2.15.0; extra == "dev"
Provides-Extra: docs
Requires-Dist: sphinx>=4.0.0; extra == "docs"
Requires-Dist: sphinx-rtd-theme>=0.5.0; extra == "docs"
Requires-Dist: myst-parser>=0.15.0; extra == "docs"
Provides-Extra: uv
Requires-Dist: uv>=0.1.0; extra == "uv"
Provides-Extra: all
Requires-Dist: uv>=0.1.0; extra == "all"
Requires-Dist: pytest>=6.2.0; extra == "all"
Requires-Dist: pytest-cov>=2.12.0; extra == "all"
Requires-Dist: black>=21.0.0; extra == "all"
Requires-Dist: flake8>=3.9.0; extra == "all"
Requires-Dist: mypy>=0.910; extra == "all"
Requires-Dist: isort>=5.9.0; extra == "all"
Requires-Dist: pre-commit>=2.15.0; extra == "all"
Requires-Dist: sphinx>=4.0.0; extra == "all"
Requires-Dist: sphinx-rtd-theme>=0.5.0; extra == "all"
Requires-Dist: myst-parser>=0.15.0; extra == "all"
Dynamic: author
Dynamic: author-email
Dynamic: classifier
Dynamic: description
Dynamic: description-content-type
Dynamic: home-page
Dynamic: keywords
Dynamic: license-file
Dynamic: project-url
Dynamic: provides-extra
Dynamic: requires-dist
Dynamic: requires-python
Dynamic: summary
